{"ei489": "e1", "ei490": "e2", "ei491": "e97", "ei495": "e51", "ei497": "e6", "ei498": "e52", "ei501": "e7", "ei503": "e8", "ei504": "e9", "ei505": "e10", "ei506": "e55", "ei507": "e57", "ei508": "e14", "ei509": "e15", "ei511": "e59", "ei512": "e16", "ei515": "e69", "ei517": "e21", "ei519": "e23", "ei520": "e24", "ei522": "e27", "ei523": "e28", "ei524": "e65", "ei525": "e29", "ei526": "e72", "ei529": "e30", "ei530": "e31", "ei531": "e66", "ei532": "e67", "ei533": "e32", "ei534": "e75", "ei535": "e76", "ei536": "e77", "ei538": "e79", "ei541": "e35", "ei542": "e36", "ei544": "e37", "ei545": "e358", "ei546": "e38", "ei548": "e39", "ei551": "e360", "ei554": "e363"}